seistron/__init__.py
seistron/data/__init__.py
seistron/data/clusters.py
seistron/data/data.py
seistron/data/red_giants.py
seistron/data/rr_lyraes.py
seistron/emulate/__init__.py
seistron/hpc/__init__.py
seistron/models/__init__.py
seistron/sample/__init__.py
seistron/utils/__init__.py
seistron/utils/labels.py
seistron/visualize/__init__.py
seistron-0.0.2.dist-info/LICENSE
seistron-0.0.2.dist-info/METADATA
seistron-0.0.2.dist-info/WHEEL
seistron-0.0.2.dist-info/top_level.txt
seistron-0.0.2.dist-info/RECORD
