Metadata-Version: 2.1
Name: seistron
Version: 0.0.2
Summary: An open-science package for stellar phenomenology
Home-page: https://github.com/earlbellinger/seistron
Author: Earl Patrick Bellinger
Author-email: Earl Patrick Bellinger <earl.bellinger@yale.edu>
License: MIT License
Project-URL: homepage, https://github.com/earlbellinger/seistron
Project-URL: tracker, https://github.com/earlbellinger/seistron/issues
Project-URL: documentation, https://seistron.readthedocs.io/
Keywords: seistron
Classifier: Development Status :: 2 - Pre-Alpha
Classifier: Intended Audience :: Science/Research
Classifier: License :: OSI Approved :: MIT License
Classifier: Natural Language :: English
Classifier: Programming Language :: Python :: 3
Classifier: Programming Language :: Python :: 3.9
Classifier: Programming Language :: Python :: 3.10
Classifier: Programming Language :: Python :: 3.11
Classifier: Programming Language :: Python :: 3.12
Classifier: Topic :: Scientific/Engineering :: Astronomy
Classifier: Topic :: Scientific/Engineering :: Physics
Requires-Python: >=3.6
License-File: LICENSE
Requires-Dist: pandas (>=1.3.4)
Requires-Dist: numpy (>=1.20.3)
Requires-Dist: tqdm (>=4.62.3)
Requires-Dist: matplotlib (>=3.4.3)
Requires-Dist: ipywidgets (>=8.0.4)
